bleach/__init__.py
bleach/__main__.py
bleach/config.py
bleach/cli/__init__.py
bleach/cli/args.py
bleach/commands/__init__.py
bleach/commands/branch.py
bleach/commands/pullrequest.py
bleach/formatters/__init__.py
bleach/formatters/oldest_requests.py
bleach/models/__init__.py
bleach/models/pullrequest.py
bleach/outputs/__init__.py
bleach/outputs/slack.py
bleach/outputs/stdout.py
bleach/sourcecontrol/__init__.py
bleach/sourcecontrol/bitbucket_cloud.py
bleach/sourcecontrol/github.py
bleachrepo-0.0.24.dist-info/LICENSE
bleachrepo-0.0.24.dist-info/METADATA
bleachrepo-0.0.24.dist-info/WHEEL
bleachrepo-0.0.24.dist-info/top_level.txt
bleachrepo-0.0.24.dist-info/RECORD
