Metadata-Version: 2.1
Name: bleachrepo
Version: 0.0.24
Summary: Find and remove the mold from your source control repositories
Home-page: https://github.com/shesekino/bleach
Author: Amir Moualem
Author-email: amoualem@gmail.com
License: UNKNOWN
Platform: UNKNOWN
Classifier: Programming Language :: Python :: 3
Classifier: License :: OSI Approved :: MIT License
Classifier: Operating System :: OS Independent
Requires-Dist: requests
Requires-Dist: python-dateutil
Requires-Dist: pytz
